py_aws_client/__init__.py
py_aws_client/pyawsclient.py
py_aws_client/clients/__init__.py
py_aws_client/clients/asg.py
py_aws_client/clients/cloudtrail.py
py_aws_client/clients/cloudwatch.py
py_aws_client/clients/config.py
py_aws_client/clients/dynamodb.py
py_aws_client/clients/ec2.py
py_aws_client/clients/ecs.py
py_aws_client/clients/elbv2.py
py_aws_client/clients/glue.py
py_aws_client/clients/iam.py
py_aws_client/clients/s3.py
py_aws_client/clients/secrets_manager.py
py_aws_client/clients/ses.py
py_aws_client/clients/sns.py
py_aws_client/clients/sqs.py
py_aws_client/clients/ssm.py
py_aws_client-0.0.1.dist-info/LICENSE
py_aws_client-0.0.1.dist-info/METADATA
py_aws_client-0.0.1.dist-info/WHEEL
py_aws_client-0.0.1.dist-info/top_level.txt
py_aws_client-0.0.1.dist-info/RECORD
