Metadata-Version: 2.1
Name: py-aws-client
Version: 0.0.1
Summary: py-aws-client is a Python package that simplifies the process of creating and interacting with various AWS API service clients by providing a high-level wrapper for the Boto3 AWS SDK. It includes pre-configured clients for commonly used AWS services and handles common AWS authentication mechanisms. Suitable for both novice and experienced developers looking to integrate AWS services into their Python applications.
Home-page: https://github.com/ladycami/py-aws-client
License: MIT
Keywords: aws,boto3,python
Classifier: License :: OSI Approved :: MIT License
Classifier: Programming Language :: Python :: 3
Classifier: Operating System :: OS Independent
Requires-Python: >=3.6
License-File: LICENSE
